README.md
setup.py
taktent/constants.py
taktent.egg-info/PKG-INFO
taktent.egg-info/SOURCES.txt
taktent.egg-info/dependency_links.txt
taktent.egg-info/not-zip-safe
taktent.egg-info/requires.txt
taktent.egg-info/top_level.txt
taktent/agents/__init__.py
taktent/agents/agent.py
taktent/agents/observer.py
taktent/agents/transmitter.py
taktent/agents/vector.py
taktent/populations/__init__.py
taktent/populations/population.py
taktent/strategies/__init__.py
taktent/strategies/pointingStrategy.py
taktent/strategies/scanningStrategy.py
taktent/strategies/strategy.py