Metadata-Version: 1.0
Name: taktent
Version: 1.13
Summary: A framework for conducting agent-based simulations of SETI
Home-page: http://github.com/dh4gan/taktent
Author: Duncan Forgan
Author-email: dh4gan@gmail.com
License: GPL-3.0
Platform: UNKNOWN
